python-queue-reader/MessageBrokers.py
python-queue-reader/__init__.py
python_queue_reader/MessageBrokers.py
python_queue_reader/__init__.py
python_queue_reader-1.2.dist-info/METADATA
python_queue_reader-1.2.dist-info/WHEEL
python_queue_reader-1.2.dist-info/top_level.txt
python_queue_reader-1.2.dist-info/RECORD
