Metadata-Version: 2.1
Name: python-queue-reader
Version: 1.2
Summary: Queue reader for python abstracting message brokers such as RabbitMQ
Home-page: UNKNOWN
Author: uug.ai
Author-email: 
License: UNKNOWN
Platform: UNKNOWN
Requires-Dist: boto3 (==1.34.110)
Requires-Dist: botocore (==1.34.110)
Requires-Dist: confluent-kafka (==2.4.0)
Requires-Dist: jmespath (==1.0.1)
Requires-Dist: pika (==1.3.2)
Requires-Dist: python-dateutil (==2.9.0.post0)
Requires-Dist: s3transfer (==0.10.1)
Requires-Dist: setuptools (==70.0.0)
Requires-Dist: six (==1.16.0)
Requires-Dist: urllib3 (==2.2.1)
